roamnerd.py
roamnerd-0.1.9.dist-info/entry_points.txt
roamnerd-0.1.9.dist-info/WHEEL
roamnerd-0.1.9.dist-info/METADATA
roamnerd-0.1.9.dist-info/RECORD
